jonas/__init__.py
jonas/__main__.py
jonas/cli.py
jonas/shell_tools.py
jonas-1.4.5.dist-info/licenses/LICENSE
jonas-1.4.5.dist-info/METADATA
jonas-1.4.5.dist-info/WHEEL
jonas-1.4.5.dist-info/entry_points.txt
jonas-1.4.5.dist-info/top_level.txt
jonas-1.4.5.dist-info/RECORD
