Metadata-Version: 2.4
Name: jonas
Version: 1.4.5
Summary: JONAS - Just Operate Nicely And Securely: Ein intelligenter Shell-Assistent mit OpenAI Integration
Author-email: Peter Filz <peter.filz@googlemail.com>
License: GPL-3.0-or-later
Project-URL: Homepage, https://github.com/peter-filz/jonas
Project-URL: Repository, https://github.com/peter-filz/jonas
Project-URL: Issues, https://github.com/peter-filz/jonas/issues
Keywords: shell,assistant,ai,openai,cli,automation
Classifier: Development Status :: 5 - Production/Stable
Classifier: Intended Audience :: Developers
Classifier: Intended Audience :: System Administrators
Classifier: License :: OSI Approved :: GNU General Public License v3 or later (GPLv3+)
Classifier: Operating System :: MacOS
Classifier: Operating System :: POSIX :: Linux
Classifier: Programming Language :: Python :: 3
Classifier: Programming Language :: Python :: 3.8
Classifier: Programming Language :: Python :: 3.9
Classifier: Programming Language :: Python :: 3.10
Classifier: Programming Language :: Python :: 3.11
Classifier: Programming Language :: Python :: 3.12
Classifier: Topic :: System :: Shells
Classifier: Topic :: Utilities
Requires-Python: >=3.8
License-File: LICENSE
Requires-Dist: openai>=1.0.0
Requires-Dist: pydantic>=2.7.0
Requires-Dist: rich>=13.7.0
Requires-Dist: tiktoken>=0.5.0
Requires-Dist: typer>=0.12
Provides-Extra: dev
Requires-Dist: pytest>=7.0; extra == "dev"
Requires-Dist: black>=23.0; extra == "dev"
Requires-Dist: flake8>=6.0; extra == "dev"
Dynamic: license-file
